Metadata-Version: 1.0
Name: inweather-station
Version: 0.0.1
Summary: micropython add a little game
Home-page: UNKNOWN
Author: David Huang
Author-email: menghua0416@hotmail.com
License: MIT
Platform: UNKNOWN
